{
    "cube_level_params": [
        {
            "freq": 8.56643879619726,
            "noise_sigma": 0.15178138651263487,
            "num_gaussians": 7,
            "num_faults_generated": 3,
            "max_disp_used": 86.0
        },
        {
            "freq": 20.56349890442192,
            "noise_sigma": 0.49717853672871754,
            "num_gaussians": 10,
            "num_faults_generated": 0,
            "max_disp_used": 75.0
        },
        {
            "freq": 21.97285344674784,
            "noise_sigma": 0.25719303543661043,
            "num_gaussians": 7,
            "num_faults_generated": 0,
            "max_disp_used": 78.0
        }
    ],
    "all_fault_params": [
        {
            "disp_magnitude_per_cube": 86.0,
            "applied_disp_signed": -86.0,
            "vertical_disp_component": 50.10089716741303,
            "strike": 290.38567904916823,
            "dip": 54.36859417483197,
            "slip_sign": -1,
            "fault_type": "Normal"
        },
        {
            "disp_magnitude_per_cube": 86.0,
            "applied_disp_signed": 86.0,
            "vertical_disp_component": -64.17526279915465,
            "strike": 137.91609135935644,
            "dip": 41.73566195058858,
            "slip_sign": 1,
            "fault_type": "Inverse"
        },
        {
            "disp_magnitude_per_cube": 86.0,
            "applied_disp_signed": 86.0,
            "vertical_disp_component": -41.68229394205327,
            "strike": 148.70916214299484,
            "dip": 61.00863270643754,
            "slip_sign": 1,
            "fault_type": "Inverse"
        }
    ]
}